MLDashboard/MLCallbacksBackend.py
MLDashboard/MLCommunicationBackend.py
MLDashboard/MLDashboardBackend.py
MLDashboard/DashboardModules/ControlButtons.py
MLDashboard/DashboardModules/EmptyModule.py
MLDashboard/DashboardModules/ImageModule.py
MLDashboard/DashboardModules/LossMetricsGraph.py
MLDashboard/DashboardModules/LossMetricsNumerical.py
MLDashboard/DashboardModules/Module.py
MLDashboard/DashboardModules/PredImages.py
MLDashboard/DashboardModules/StatusModule.py
MLDashboard/DashboardModules/TrainingSetSampleImages.py
MLDashboard/DashboardModules/WrongPredImages.py
MLDashboard/Examples/CustomCallbacksDemo.py
MLDashboard/Examples/InteractiveDashboardDemo.py
MLDashboard/Examples/allmodules.json
MLDashboard/Examples/dashboarddemo.json
MLDashboard/Guides/CustomCallbacks.md
MLDashboard/Guides/CustomModules.md
MLDashboard/Guides/Customization.md
MLDashboard/Guides/DataStructures.md
MLDashboard/Guides/DataStructuresDiagram.png
MLDashboard/Guides/Functions.md
MLDashboard-1.4.4.dist-info/LICENSE
MLDashboard-1.4.4.dist-info/METADATA
MLDashboard-1.4.4.dist-info/WHEEL
MLDashboard-1.4.4.dist-info/top_level.txt
MLDashboard-1.4.4.dist-info/RECORD
