Metadata-Version: 2.1
Name: MLDashboard
Version: 1.4.4
Summary: Machine learning dashboard that integrates with tensorflow. Great for monitoring training. Has tools for classification and images
Home-page: https://github.com/RobertJN64/MLDashboard
Author: Robert Nies
Author-email: robertjnies@gmail.com
License: MIT
Classifier: Programming Language :: Python
Classifier: Programming Language :: Python :: 3
Classifier: Programming Language :: Python :: 3 :: Only
Classifier: Programming Language :: Python :: 3.8
Classifier: Programming Language :: Python :: 3.9
Classifier: Programming Language :: Python :: 3.10
Classifier: Programming Language :: Python :: 3.11
Classifier: Programming Language :: Python :: 3.12
Requires-Python: >=3.8
License-File: LICENSE
Requires-Dist: matplotlib
Requires-Dist: tensorflow
Requires-Dist: numpy
Requires-Dist: pillow
